cwl_oscar/README.md
cwl_oscar/__init__.py
cwl_oscar/_version.py
cwl_oscar/cluster_manager.py
cwl_oscar/command_line_tool.py
cwl_oscar/constants.py
cwl_oscar/context_utils.py
cwl_oscar/executor.py
cwl_oscar/factory.py
cwl_oscar/lib-calls.py
cwl_oscar/local_runner.py
cwl_oscar/main.py
cwl_oscar/oscar.py
cwl_oscar/path_mapper.py
cwl_oscar/service_manager.py
cwl_oscar/task.py
cwl_oscar/test_oscar.py
cwl_oscar/utils.py
cwl_oscar/docs/README.md
cwl_oscar/docs/communication-sequence.mmd
cwl_oscar/docs/component-architecture.mmd
cwl_oscar/docs/execution-flow.mmd
cwl_oscar/example/cat_hosts.cwl
cwl_oscar/example/date.cwl
cwl_oscar/example/empty_input.json
cwl_oscar/example/grep.cwl
cwl_oscar/example/grep_input.json
cwl_oscar/example/hello copy.cwl
cwl_oscar/example/hello.cwl
cwl_oscar/example/input.json
cwl_oscar/example/input_hello.json
cwl_oscar/example/reverse-workflow.cwl
cwl_oscar/example/simple-workflow-input.json
cwl_oscar/example/simple-workflow-no-input.json
cwl_oscar/example/simple-workflow.cwl
cwl_oscar/example/touch_ls.cwl
cwl_oscar/example/uname.cwl
cwl_oscar/example/whoami.cwl
cwl_oscar/example/malaria-cwl-portable-package/.gitignore
cwl_oscar/example/malaria-cwl-portable-package/README.md
cwl_oscar/example/malaria-cwl-portable-package/diagram.png
cwl_oscar/example/malaria-cwl-portable-package/diagram2.png
cwl_oscar/example/malaria-cwl-portable-package/diagram3.png
cwl_oscar/example/malaria-cwl-portable-package/make-diagrams.sh
cwl_oscar/example/malaria-cwl-portable-package/examples/oscar-dual-samples-input.yml
cwl_oscar/example/malaria-cwl-portable-package/examples/oscar-single-dhfr-input.yml
cwl_oscar/example/malaria-cwl-portable-package/examples/portable-single-sample.yml
cwl_oscar/example/malaria-cwl-portable-package/examples/portable-test-input.yml
cwl_oscar/example/malaria-cwl-portable-package/examples/test-integrated-input.yml
cwl_oscar/example/malaria-cwl-portable-package/examples/test-multiple-samples.yml
cwl_oscar-0.1.1.dist-info/licenses/LICENSE
cwl_oscar-0.1.1.dist-info/METADATA
cwl_oscar-0.1.1.dist-info/WHEEL
cwl_oscar-0.1.1.dist-info/entry_points.txt
cwl_oscar-0.1.1.dist-info/top_level.txt
cwl_oscar-0.1.1.dist-info/RECORD
