Metadata-Version: 2.4
Name: cwl-oscar
Version: 0.1.1
Summary: A lightweight Workflow Management System to Orchestrate CWL Workflows on OSCAR clusters
Requires-Python: >=3.12
License-File: LICENSE
Requires-Dist: cwltest>=2.6.20250314152537
Requires-Dist: cwltool>=3.1.20250715140722
Requires-Dist: future>=0.16.0
Requires-Dist: minio>=7.2.0
Requires-Dist: oscar-python>=1.3.1
Requires-Dist: pydantic>=2.0.0
Requires-Dist: pyjwt>=1.6.4
Requires-Dist: python-dotenv>=0.19.0
Requires-Dist: requests>=2.18.2
Requires-Dist: typing-extensions>=3.7.4
Dynamic: license-file
